LICENSE
MANIFEST.in
README.rst
setup.cfg
setup.py
django_tota11y.egg-info/PKG-INFO
django_tota11y.egg-info/SOURCES.txt
django_tota11y.egg-info/dependency_links.txt
django_tota11y.egg-info/not-zip-safe
django_tota11y.egg-info/requires.txt
django_tota11y.egg-info/top_level.txt
tota11y/__init__.py
tota11y/middleware.py
tota11y/models.py
tota11y/static/tota11y/js/tota11y.min.js
tota11y/templates/tota11y/base.html