Metadata-Version: 1.1
Name: django-tota11y
Version: 0.1.1
Summary: Easy to install Django app for tota11y - an accessibility visualization toolkit by Khan Academy (http://khan.github.io/tota11y/).
Home-page: https://github.com/hiisi13/django-tota11y
Author: Dmitry Kozhedubov
Author-email: hiisi13@gmail.com
License: MIT
Keywords: accessibility,visualization
Platform: UNKNOWN
Classifier: Development Status :: 2 - Pre-Alpha
Classifier: Framework :: Django
Classifier: Intended Audience :: Developers
Classifier: License :: OSI Approved :: BSD License
Classifier: Natural Language :: English
Classifier: Programming Language :: Python :: 2
Classifier: Programming Language :: Python :: 2.6
Classifier: Programming Language :: Python :: 2.7
Classifier: Programming Language :: Python :: 3
Classifier: Programming Language :: Python :: 3.3
